LICENSE
MANIFEST.in
README
setup.py
debug_toolbar_mongo/__init__.py
debug_toolbar_mongo/operation_tracker.py
debug_toolbar_mongo/panel.py
flask_debug_toolbar_mongo.egg-info/PKG-INFO
flask_debug_toolbar_mongo.egg-info/SOURCES.txt
flask_debug_toolbar_mongo.egg-info/dependency_links.txt
flask_debug_toolbar_mongo.egg-info/not-zip-safe
flask_debug_toolbar_mongo.egg-info/requires.txt
flask_debug_toolbar_mongo.egg-info/top_level.txt
templates/mongo-panel.html