Metadata-Version: 1.0
Name: flask-debug-toolbar-mongo
Version: 0.0.1
Summary: flask debug toolbar for mongodb.
Home-page: https://github.com/endsh/flask-debug-toolbar-mongo
Author: Linshao
Author-email: 438985635@qq.com
License: UNKNOWN
Platform: any
